ctao_datapipe-0.3.1.dist-info/licenses/AUTHORS
ctao_datapipe-0.3.1.dist-info/licenses/LICENSE
datapipe/__init__.py
datapipe/_version.py
datapipe/version.py
datapipe/tests/__init__.py
datapipe/tests/test_version.py
datapipe/tests/utils.py
ctao_datapipe-0.3.1.dist-info/METADATA
ctao_datapipe-0.3.1.dist-info/WHEEL
ctao_datapipe-0.3.1.dist-info/top_level.txt
ctao_datapipe-0.3.1.dist-info/RECORD
